<annotation>
	<folder>allimages</folder>
	<filename>IMG_20220114_121803.jpg</filename>
	<path>/Users/dimmat/Documents/Mitko/Fontys/SmartMobile/Repo/ImageDetectionRepos/RealTimeObjectDetection/Tensorflow/workspace/images/allimages/IMG_20220114_121803.jpg</path>
	<source>
		<database>Unknown</database>
	</source>
	<size>
		<width>4000</width>
		<height>3000</height>
		<depth>3</depth>
	</size>
	<segmented>0</segmented>
	<object>
		<name>usbport_in</name>
		<pose>Unspecified</pose>
		<truncated>0</truncated>
		<difficult>0</difficult>
		<bndbox>
			<xmin>1375</xmin>
			<ymin>1400</ymin>
			<xmax>1806</xmax>
			<ymax>1640</ymax>
		</bndbox>
	</object>
	<object>
		<name>usbport_in</name>
		<pose>Unspecified</pose>
		<truncated>0</truncated>
		<difficult>0</difficult>
		<bndbox>
			<xmin>2012</xmin>
			<ymin>1447</ymin>
			<xmax>2450</xmax>
			<ymax>1706</ymax>
		</bndbox>
	</object>
</annotation>
